README
setup.py
svargaext.transform.egg-info/PKG-INFO
svargaext.transform.egg-info/SOURCES.txt
svargaext.transform.egg-info/dependency_links.txt
svargaext.transform.egg-info/namespace_packages.txt
svargaext.transform.egg-info/requires.txt
svargaext.transform.egg-info/top_level.txt
svargaext/transform/__init__.py
svargaext/transform/backends.py
svargaext/transform/commands.py
svargaext/transform/templating.py