Metadata-Version: 1.0
Name: svargaext.transform
Version: 0.6
Summary: Source transformation module for Svarga framework
Home-page: http://hg.piranha.org.ua/svargaext.transform/
Author: Alexander Solovyov
Author-email: alexander@solovyov.net
License: BSD
Platform: any
Classifier: Environment :: Web Environment
Classifier: Intended Audience :: Developers
Classifier: License :: OSI Approved :: BSD License
Classifier: Operating System :: OS Independent
Classifier: Programming Language :: Python
Classifier: Topic :: Internet :: WWW/HTTP :: Dynamic Content
Classifier: Topic :: Software Development :: Libraries :: Python Modules
